rendarr/__init__.py
rendarr/cli.py
rendarr/main.py
rendarr-0.2.1.dist-info/METADATA
rendarr-0.2.1.dist-info/WHEEL
rendarr-0.2.1.dist-info/entry_points.txt
rendarr-0.2.1.dist-info/top_level.txt
rendarr-0.2.1.dist-info/RECORD
