Metadata-Version: 2.4
Name: rendarr
Version: 0.2.1
Summary: Render a slice of a .npy array as an image.
Requires-Python: >=3.6
Requires-Dist: numpy>=1.11
Requires-Dist: matplotlib>=1.5.0
